EastRY/__init__.py
EastRY/a.py
eastinstaller24-1.0.0.dist-info/METADATA
eastinstaller24-1.0.0.dist-info/WHEEL
eastinstaller24-1.0.0.dist-info/entry_points.txt
eastinstaller24-1.0.0.dist-info/top_level.txt
eastinstaller24-1.0.0.dist-info/RECORD
