Metadata-Version: 2.4
Name: eastinstaller24
Version: 1.0.0
Summary: EastInstaller24 - a lightweight pip wrapper CLI
Author-email: "Xscripts, Inc. (BB)" <sunnyplaysyt9@gmail.com>
Requires-Python: >=3.7
